Workbook

Sheet Summary
A1: LIVING WATER NETWORK INC.
A2: Year One Budget Summary (Apr 2026 - Mar 2027)
A4: Category | B4: Budget Low | C4: Budget Target | D4: Budget Stretch
A5: REVENUE
A6: Gala: Monthly Donor Commitments (annualized) | B6: 60000 | C6: 120000 | D6: 180000
A7: Gala: One-Time Gifts (in-room) | B7: 5000 | C7: 10000 | D7: 20000
A8: Sponsorships: Title | B8: 15000 | C8: 25000 | D8: 30000
A9: Sponsorships: Presenting | B9: 0 | C9: 10000 | D9: 20000
A10: Sponsorships: Table | B10: 5000 | C10: 15000 | D10: 30000
A11: Sponsorships: Impact | B11: 1000 | C11: 4000 | D11: 8000
A12: Major Gifts (outside gala) | B12: 5000 | C12: 15000 | D12: 35000
A13: Cohort Tuition (earned) | B13: 3000 | C13: 10000 | D13: 25000
A14: Speaking / Leadership Intensives | B14: 1000 | C14: 3000 | D14: 8000
A15: Church Partnership Fees | B15: 0 | C15: 2000 | D15: 6000
A16: Grants (opportunistic) | B16: 0 | C16: 0 | D16: 15000
A17: TOTAL REVENUE | B17: =SUM(B6:B16) | C17: =SUM(C6:C16) | D17: =SUM(D6:D16)
A19: EXPENSES
A20: Gala Production (underwritten by title sponsor if secured) | B20: 20000 | C20: 25000 | D20: 30000
A21: Programs: Cohort Delivery (facilitators, materials, space) | B21: 5000 | C21: 10000 | D21: 18000
A22: Missions: Ecuador Trip (pre-funded by participants + sponsors) | B22: 8000 | C22: 15000 | D22: 25000
A23: Personnel / Contractors (Ops, Dev, Programs) | B23: 20000 | C23: 40000 | D23: 70000
A24: Marketing / Brand (design, video, photography) | B24: 5000 | C24: 10000 | D24: 18000
A25: Website, CRM, Email, Software Stack | B25: 3000 | C25: 6000 | D25: 10000
A26: Legal, Accounting, Insurance, Compliance | B26: 3000 | C26: 6000 | D26: 10000
A27: Travel, Meals, Donor Cultivation | B27: 2000 | C27: 5000 | D27: 10000
A28: Office / Admin / Banking Fees / Processing | B28: 1500 | C28: 3000 | D28: 6000
A29: Board + Staff Development | B29: 500 | C29: 2000 | D29: 5000
A30: Contingency Reserve (10%) | B30: 3000 | C30: 7000 | D30: 15000
A31: TOTAL EXPENSES | B31: =SUM(B20:B30) | C31: =SUM(C20:C30) | D31: =SUM(D20:D30)
A33: NET SURPLUS / (DEFICIT) | B33: =B17-B31 | C33: =C17-C31 | D33: =D17-D31
A36: Notes
A37: Low = conservative quiet-phase outcome. Target = stated Year One plan ($100K-$180K band). Stretch = upside with full sponsor + cohort performance.
A38: Gala production is shown as gross cost; if title sponsor underwrites, it becomes a pass-through and revenue/expense net to zero for that line.
A39: Missions trip expense is participant-funded; cost shown for transparency but should break even.
A40: All figures in USD. Edit directly; totals recalculate.

Sheet Revenue by Month
A1: Revenue Plan by Month (Target Scenario)
A3: Revenue Stream | B3: Apr-26 | C3: May-26 | D3: Jun-26 | E3: Jul-26 | F3: Aug-26 | G3: Sep-26 | H3: Oct-26 | I3: Nov-26 | J3: Dec-26 | K3: Jan-27 | L3: Feb-27 | M3: Mar-27 | N3: Total
A4: Monthly Donor Revenue (cumulative) | B4: 0 | C4: 0 | D4: 1000 | E4: 1500 | F4: 2500 | G4: 4000 | H4: 6000 | I4: 10000 | J4: 12000 | K4: 13000 | L4: 14000 | M4: 15000 | N4: =SUM(B4:M4)
A5: One-Time Gifts / Year-End | B5: 0 | C5: 500 | D5: 500 | E5: 1000 | F5: 1000 | G5: 2000 | H5: 3000 | I5: 15000 | J5: 5000 | K5: 2000 | L5: 1000 | M5: 1000 | N5: =SUM(B5:M5)
A6: Sponsorship Payments | B6: 0 | C6: 0 | D6: 0 | E6: 5000 | F6: 10000 | G6: 15000 | H6: 15000 | I6: 10000 | J6: 0 | K6: 0 | L6: 0 | M6: 0 | N6: =SUM(B6:M6)
A7: Cohort Tuition | B7: 0 | C7: 0 | D7: 4000 | E7: 0 | F7: 0 | G7: 0 | H7: 0 | I7: 0 | J7: 0 | K7: 4000 | L7: 0 | M7: 2000 | N7: =SUM(B7:M7)
A8: Major Gifts | B8: 0 | C8: 2000 | D8: 2000 | E8: 3000 | F8: 3000 | G8: 2000 | H8: 2000 | I8: 2000 | J8: 2000 | K8: 1000 | L8: 1000 | M8: 1000 | N8: =SUM(B8:M8)
A9: Speaking / Intensives | B9: 0 | C9: 0 | D9: 500 | E9: 500 | F9: 0 | G9: 500 | H9: 0 | I9: 500 | J9: 500 | K9: 500 | L9: 500 | M9: 500 | N9: =SUM(B9:M9)
A10: Church Partnership Fees | B10: 0 | C10: 0 | D10: 0 | E10: 500 | F10: 500 | G10: 500 | H10: 0 | I10: 0 | J10: 0 | K10: 500 | L10: 0 | M10: 0 | N10: =SUM(B10:M10)
A11: MONTHLY TOTAL | B11: =SUM(B4:B10) | C11: =SUM(C4:C10) | D11: =SUM(D4:D10) | E11: =SUM(E4:E10) | F11: =SUM(F4:F10) | G11: =SUM(G4:G10) | H11: =SUM(H4:H10) | I11: =SUM(I4:I10) | ... M11: =SUM(M4:M10) | N11: =SUM(B11:M11)

Sheet Expenses by Month
A1: Expense Plan by Month (Target Scenario)
A3: Revenue Stream | B3: Apr-26 | C3: May-26 | D3: Jun-26 | E3: Jul-26 | F3: Aug-26 | G3: Sep-26 | H3: Oct-26 | I3: Nov-26 | J3: Dec-26 | K3: Jan-27 | L3: Feb-27 | M3: Mar-27 | N3: Total
A4: Gala Production | B4: 0 | C4: 0 | D4: 500 | E4: 1500 | F4: 3000 | G4: 5000 | H4: 7000 | I4: 8000 | J4: 0 | K4: 0 | L4: 0 | M4: 0 | N4: =SUM(B4:M4)
A5: Programs: Cohort Delivery | B5: 500 | C5: 500 | D5: 1500 | E5: 1000 | F5: 1000 | G5: 1000 | H5: 500 | I5: 500 | J5: 500 | K5: 1500 | L5: 500 | M5: 1000 | N5: =SUM(B5:M5)
A6: Missions: Ecuador Trip | B6: 0 | C6: 0 | D6: 500 | E6: 500 | F6: 1000 | G6: 1500 | H6: 2000 | I6: 2500 | J6: 1500 | K6: 2500 | L6: 2500 | M6: 500 | N6: =SUM(B6:M6)
A7: Personnel / Contractors | B7: 2500 | C7: 3000 | D7: 3500 | E7: 3500 | F7: 3500 | G7: 4000 | H7: 4000 | I7: 4000 | J7: 3500 | K7: 3000 | L7: 3000 | M7: 2500 | N7: =SUM(B7:M7)
A8: Marketing / Brand | B8: 500 | C8: 750 | D8: 1000 | E8: 1000 | F8: 1000 | G8: 1500 | H8: 1500 | I8: 1500 | J8: 500 | K8: 250 | L8: 250 | M8: 250 | N8: =SUM(B8:M8)
A9: Software / CRM / Email | B9: 500 | C9: 500 | D9: 500 | E9: 500 | F9: 500 | G9: 500 | H9: 500 | I9: 500 | J9: 500 | K9: 500 | L9: 500 | M9: 500 | N9: =SUM(B9:M9)
A10: Legal / Accounting / Insurance | B10: 500 | C10: 500 | D10: 500 | E10: 500 | F10: 500 | G10: 500 | H10: 500 | I10: 500 | J10: 500 | K10: 500 | L10: 500 | M10: 500 | N10: =SUM(B10:M10)
A11: Travel / Cultivation | B11: 250 | C11: 500 | D11: 500 | E11: 500 | F11: 500 | G11: 500 | H11: 750 | I11: 500 | J11: 250 | K11: 250 | L11: 250 | M11: 250 | N11: =SUM(B11:M11)
A12: Office / Admin / Fees | B12: 250 | C12: 250 | D12: 250 | E12: 250 | F12: 250 | G12: 250 | H12: 250 | I12: 250 | J12: 250 | K12: 250 | L12: 250 | M12: 250 | N12: =SUM(B12:M12)
A13: Board / Staff Development | B13: 100 | C13: 100 | D13: 200 | E13: 200 | F13: 200 | G13: 200 | H13: 200 | I13: 200 | J13: 200 | K13: 100 | L13: 100 | M13: 200 | N13: =SUM(B13:M13)
A14: Contingency Reserve | B14: 500 | C14: 500 | D14: 500 | E14: 500 | F14: 500 | G14: 500 | H14: 500 | I14: 500 | J14: 500 | K14: 500 | L14: 500 | M14: 500 | N14: =SUM(B14:M14)
A15: MONTHLY TOTAL | B15: =SUM(B4:B14) | C15: =SUM(C4:C14) | D15: =SUM(D4:D14) | E15: =SUM(E4:E14) | F15: =SUM(F4:F14) | G15: =SUM(G4:G14) | H15: =SUM(H4:H14) | I15: =SUM(I4:I14) | ... M15: =SUM(M4:M14) | N15: =SUM(B15:M15)

Sheet Cash Flow
A1: Cash Flow Forecast (Target Scenario)
A2: Links to Revenue by Month and Expenses by Month sheets
A4: Revenue Stream | B4: Apr-26 | C4: May-26 | D4: Jun-26 | E4: Jul-26 | F4: Aug-26 | G4: Sep-26 | H4: Oct-26 | I4: Nov-26 | J4: Dec-26 | K4: Jan-27 | L4: Feb-27 | M4: Mar-27 | N4: Total
A5: Opening Cash Balance (assumption) | B5: 5000 | C5: =B9 | D5: =C9 | E5: =D9 | F5: =E9 | G5: =F9 | H5: =G9 | I5: =H9 | J5: =I9 | ... M5: =L9 | N5: =B5
A6: + Revenue | B6: ='Revenue by Month'!B11 | C6: ='Revenue by Month'!C11 | D6: ='Revenue by Month'!D11 | E6: ='Revenue by Month'!E11 | F6: ='Revenue by Month'!F11 | G6: ='Revenue by Month'!G11 | H6: ='Revenue by Month'!H11 | I6: ='Revenue by Month'!I11 | ... M6: ='Revenue by Month'!M11 | N6: =SUM(B6:M6)
A7: - Expenses | B7: ='Expenses by Month'!B15 | C7: ='Expenses by Month'!C15 | D7: ='Expenses by Month'!D15 | E7: ='Expenses by Month'!E15 | F7: ='Expenses by Month'!F15 | G7: ='Expenses by Month'!G15 | H7: ='Expenses by Month'!H15 | I7: ='Expenses by Month'!I15 | ... M7: ='Expenses by Month'!M15 | N7: =SUM(B7:M7)
A8: Net Monthly Change | B8: =B6-B7 | C8: =C6-C7 | D8: =D6-D7 | E8: =E6-E7 | F8: =F6-F7 | G8: =G6-G7 | H8: =H6-H7 | I8: =I6-I7 | ... M8: =M6-M7 | N8: =SUM(B8:M8)
A9: Ending Cash Balance | B9: =B5+B8 | C9: =C5+C8 | D9: =D5+D8 | E9: =E5+E8 | F9: =F5+F8 | G9: =G5+G8 | H9: =H5+H8 | I9: =I5+I8 | ... N9: =N5+N8
A12: Cash flow is a forecast. Update monthly with actuals. Red ending balance = cash gap to manage via timing or line of credit.

Sheet KPI Scorecard
A1: Year One KPI Scorecard
A2: Update monthly. Compare Actual to Target. Color-code trend.
A4: KPI | B4: Year 1 Target | C4: Current Actual | D4: Gap | E4: Owner
A5: Total Raised (USD) | B5: 180000 | C5: 0 | D5: =C5-B5 | E5: Development
A6: Monthly Recurring Donors (count) | B6: 150 | C6: 0 | D6: =C6-B6 | E6: Development
A7: Gala Attendees | B7: 200 | C7: 0 | D7: =C7-B7 | E7: Development
A8: Sponsor Dollars Committed | B8: 50000 | C8: 0 | D8: =C8-B8 | E8: Development
A9: Cohort Participants (total across cohorts) | B9: 75 | C9: 0 | D9: =C9-B9 | E9: Programs
A10: Cohort Completion Rate (%) | B10: 85 | C10: 0 | D10: =C10-B10 | E10: Programs
A11: Leaders Deployed to Ecuador | B11: 8 | C11: 0 | D11: =C11-B11 | E11: Missions
A12: Partner Churches (Program Partner+) | B12: 5 | C12: 0 | D12: =C12-B12 | E12: Founder
A13: Email List Size | B13: 1500 | C13: 0 | D13: =C13-B13 | E13: Marketing
A14: Donor Retention Rate (%) | B14: 80 | C14: 0 | D14: =C14-B14 | E14: Development
A15: Time-to-Thank (hours, average) | B15: 48 | C15: 0 | D15: =C15-B15 | E15: Development
A16: Cash Runway (months) | B16: 6 | C16: 0 | D16: =C16-B16 | E16: Operations
A19: How to use: update 'Current Actual' monthly. Gap shows distance to target. Discuss negative gaps at monthly finance review.
